tmac/__init__.py
tmac/asset.py
tmac/component.py
tmac/data_flow.py
tmac/diagram.py
tmac/element.py
tmac/model.py
tmac/node.py
tmac/otm.py
tmac/plus/__init__.py
tmac/plus/client_side.py
tmac/plus/data_store.py
tmac/plus/server_side.py
tmac/plus_aws/__init__.py
tmac/plus_aws/application_load_balancer.py
tmac/risk.py
tmac/score.py
tmac/table_format.py
tmac/tag.py
tmac/templates/default.tpl
tmac/threat.py
tmac/threat_library/__init__.py
tmac/threat_library/templates/user_story_templates.json
tmac/trust_boundary.py
tmac/user_story.py
tmac-0.0.9.dist-info/LICENSE
tmac-0.0.9.dist-info/WHEEL
tmac-0.0.9.dist-info/METADATA
tmac-0.0.9.dist-info/RECORD
