Metadata-Version: 2.1
Name: tmac
Version: 0.0.9
Summary: Agile Threat Modeling as Code
Home-page: https://github.com/hupe1980/tmac
License: MIT
Keywords: agile,decsecops,threat-modeling,cybersecurity,appsec,jupyter-notebook,OpenThreatModel,otm
Author: hupe1980
Requires-Python: >=3.11,<4.0
Classifier: License :: OSI Approved :: MIT License
Classifier: Programming Language :: Python
Classifier: Programming Language :: Python :: 3
Classifier: Programming Language :: Python :: 3.11
Classifier: Programming Language :: Python :: 3
Classifier: Topic :: Security
Requires-Dist: diagrams (>=0.23.1,<0.24.0)
Requires-Dist: jinja2 (>=3.1.2,<4.0.0)
Requires-Dist: tabulate (>=0.9.0,<0.10.0)
Project-URL: Repository, https://github.com/hupe1980/tmac
